odoo/addons/l10n_es_aeat_mod123/README.rst
odoo/addons/l10n_es_aeat_mod123/__init__.py
odoo/addons/l10n_es_aeat_mod123/__manifest__.py
odoo/addons/l10n_es_aeat_mod123/data/l10n.es.aeat.map.tax.line.tax.csv
odoo/addons/l10n_es_aeat_mod123/data/2016/aeat.model.export.config.csv
odoo/addons/l10n_es_aeat_mod123/data/2016/aeat.model.export.config.line.csv
odoo/addons/l10n_es_aeat_mod123/data/2016/l10n.es.aeat.map.tax.csv
odoo/addons/l10n_es_aeat_mod123/data/2016/l10n.es.aeat.map.tax.line.csv
odoo/addons/l10n_es_aeat_mod123/data/2024/aeat.model.export.config.csv
odoo/addons/l10n_es_aeat_mod123/data/2024/aeat.model.export.config.line.csv
odoo/addons/l10n_es_aeat_mod123/data/2024/l10n.es.aeat.map.tax.csv
odoo/addons/l10n_es_aeat_mod123/data/2024/l10n.es.aeat.map.tax.line.csv
odoo/addons/l10n_es_aeat_mod123/i18n/bg.po
odoo/addons/l10n_es_aeat_mod123/i18n/ca.po
odoo/addons/l10n_es_aeat_mod123/i18n/cs.po
odoo/addons/l10n_es_aeat_mod123/i18n/de.po
odoo/addons/l10n_es_aeat_mod123/i18n/es.po
odoo/addons/l10n_es_aeat_mod123/i18n/es_CO.po
odoo/addons/l10n_es_aeat_mod123/i18n/es_CR.po
odoo/addons/l10n_es_aeat_mod123/i18n/eu.po
odoo/addons/l10n_es_aeat_mod123/i18n/fr.po
odoo/addons/l10n_es_aeat_mod123/i18n/gl.po
odoo/addons/l10n_es_aeat_mod123/i18n/hr.po
odoo/addons/l10n_es_aeat_mod123/i18n/l10n_es_aeat_mod123.pot
odoo/addons/l10n_es_aeat_mod123/i18n/nl.po
odoo/addons/l10n_es_aeat_mod123/i18n/pl.po
odoo/addons/l10n_es_aeat_mod123/i18n/pt.po
odoo/addons/l10n_es_aeat_mod123/i18n/pt_BR.po
odoo/addons/l10n_es_aeat_mod123/i18n/sl.po
odoo/addons/l10n_es_aeat_mod123/i18n/sv.po
odoo/addons/l10n_es_aeat_mod123/i18n/tr.po
odoo/addons/l10n_es_aeat_mod123/i18n/vi.po
odoo/addons/l10n_es_aeat_mod123/models/__init__.py
odoo/addons/l10n_es_aeat_mod123/models/mod123.py
odoo/addons/l10n_es_aeat_mod123/readme/CONTRIBUTORS.md
odoo/addons/l10n_es_aeat_mod123/readme/DESCRIPTION.md
odoo/addons/l10n_es_aeat_mod123/readme/USAGE.md
odoo/addons/l10n_es_aeat_mod123/security/ir.model.access.csv
odoo_addon_l10n_es_aeat_mod123-18.0.1.0.3.dist-info/METADATA
odoo_addon_l10n_es_aeat_mod123-18.0.1.0.3.dist-info/WHEEL
odoo_addon_l10n_es_aeat_mod123-18.0.1.0.3.dist-info/top_level.txt
odoo_addon_l10n_es_aeat_mod123-18.0.1.0.3.dist-info/RECORD
